{
	"id": 3010,
	"slug": "jetzt-neu-kanalrichtlinien",
	"path": "/youtube-tipps-de/jetzt-neu-kanalrichtlinien/",
	"title": "Jetzt neu: Kanalrichtlinien",
	"excerpt": "So richtest du Kanalrichtlinien ein, damit neue Zuschauer Chat- und Kommentarregeln direkt verstehen.",
	"contentHtml": "<h2 class=\"wp-block-heading\">Transkript</h2>\n\n<p class=\"wp-block-paragraph\">Mit dem neuen Kanalrichtlinien Feature könnt ihr neuen Zuschauern schnell und kompakt eure Chat &amp; Kommentarregeln erklären. Um diese hinzuzufügen geht ihr in euren Einstellungen unter &quot;Community&quot; auf den Tab Kanalrichtlinien. Dort könnt ihr eine Willkommensnachricht vorgeben und bis zu 3 Textboxen für eure Richtlinien ausfüllen.</p>\n",
	"date": "2022-04-19T20:23:36",
	"modified": "2022-04-19T20:23:36",
	"locale": "de",
	"categoryIds": [
		17
	],
	"image": "https://i.ytimg.com/vi/SI8OKrwxSu8/maxresdefault.jpg",
	"authorName": "Martin Koytek",
	"sourceUrl": "https://www.youtube.com/shorts/SI8OKrwxSu8",
	"video": {
		"youtubeId": "SI8OKrwxSu8",
		"embedUrl": "https://www.youtube.com/embed/SI8OKrwxSu8",
		"watchUrl": "https://www.youtube.com/shorts/SI8OKrwxSu8",
		"thumbnailUrl": "https://i.ytimg.com/vi/SI8OKrwxSu8/maxresdefault.jpg"
	}
}
